setup.py
cary_travelcommand/__init__.py
cary_travelcommand/travel_calculations.py
cary_travelcommand/travel_costs.py
cary_travelcommand/travel_parser.py
cary_travelcommand.egg-info/PKG-INFO
cary_travelcommand.egg-info/SOURCES.txt
cary_travelcommand.egg-info/dependency_links.txt
cary_travelcommand.egg-info/requires.txt
cary_travelcommand.egg-info/top_level.txt
cary_travelcommand/fake_estimator/sample_roundtrip_request.json
cary_travelcommand/fake_estimator/sample_roundtrip_response.json
cary_travelcommand/fake_estimator/sample_single_request.json
cary_travelcommand/fake_estimator/sample_single_response.json
cary_travelcommand/templates/html_template.html
cary_travelcommand/templates/plaintext_template.txt