Metadata-Version: 1.1
Name: cary-travelcommand
Version: 1.0.0
Summary: US gov per-diem lookup for Cary
Home-page: https://github.com/vputz/cary_travelcommand
Author: Victor Putz
Author-email: vputz@nyx.net
License: MIT
Keywords: email
Platform: UNKNOWN
Classifier: Development Status :: 4 - Beta
Classifier: Intended Audience :: Developers
Classifier: Topic :: Communications :: Email
Classifier: License :: OSI Approved :: MIT License
Classifier: Programming Language :: Python :: 3
